ytdlmusic/__init__.py
ytdlmusic/batch.py
ytdlmusic/choice.py
ytdlmusic/const.py
ytdlmusic/download.py
ytdlmusic/file.py
ytdlmusic/log.py
ytdlmusic/params.py
ytdlmusic/print.py
ytdlmusic/search.py
ytdlmusic/tag.py
ytdlmusic/version.py
ytdlmusic/ytdlmusic.py
ytdlmusic-3.0.1.dist-info/LICENSE.txt
ytdlmusic-3.0.1.dist-info/METADATA
ytdlmusic-3.0.1.dist-info/WHEEL
ytdlmusic-3.0.1.dist-info/entry_points.txt
ytdlmusic-3.0.1.dist-info/top_level.txt
ytdlmusic-3.0.1.dist-info/RECORD
